Metadata-Version: 1.1
Name: IMDBAPI
Version: 1.0.2
Summary: API for IMDB, to search for movie and get the details like rating, summary, director, cast etc
Home-page: https://github.com/devilking15292/IMDB_Api_python.git
Author: devilking15292
Author-email: p.hari15292@gmail.com
License: MIT
Keywords: imdb,imdbapi,movie,movies
Platform: UNKNOWN
Classifier: Programming Language :: Python :: 3.4
Classifier: Programming Language :: Python :: 3.5
Classifier: Programming Language :: Python :: 3.6
Classifier: Topic :: Internet :: WWW/HTTP
